{
  "source": "/mnt/h/oceanwave",
  "target": "/mnt/h/oceanwave_app/oceanwave_v1.0",
  "repos": {
    "oceanseed_app":  { "path": "lib/back_ends/oceanseed_app" },
    "oceanfarm_app":  { "path": "lib/back_ends/oceanfarm_app" },
    "oceanhub_app":   { "path": "lib/back_ends/oceanhub_app" },
    "oceandata_app":  { "path": "lib/back_ends/oceandata_app" },
    "oceanlive_app":  { "path": "lib/back_ends/oceanlive_app" },

    "oceanwave_dash": { "path": "lib/front_ends/oceanwave_dash" },
    "oceanreact":     { "path": "lib/front_ends/oceanreact" },
    "oceandata_gui":  { "path": "lib/front_ends/oceandata_gui" },
    "oceanpyqt":      { "path": "lib/front_ends/oceanpyqt" },
    "oceanapp":       { "path": "lib/front_ends/oceanapp" },
    "oceandata_tau":  { "path": "lib/front_ends/oceandata_tau" },

    "jsonldb":        { "path": "lib/jsonldb" },
    "oceancap":       { "path": "lib/oceancap" },
    "oceandata":      { "path": "lib/oceandata" },
    "oceanfarm":      { "path": "lib/oceanfarm" },
    "oceanquant":     { "path": "lib/oceanquant" },
    "oceanseed":      { "path": "lib/oceanseed" },
    "oceanutil":      { "path": "lib/oceanutil" },
    "oceanshed":      { "path": "lib/oceanshed" },
    "dataportal":     { "path": "lib/dataportal" },

    "oceandata-cli":  { "path": "lib/cli/oceandata-cli" },
    "oceanlab-cli":   { "path": "lib/cli/oceanlab-cli" },

    "data_configs":   { "path": "hubs/data_configs" },
    "signal_samples": { "path": "hubs/signal_samples" },

    "scripts":        { "path": "scripts" }
  }
}
